<?xml version="1.0" encoding="UTF-8"?>
<object name="ca" meta_type="Dexterity Container">
  <criteria>
    <criterion name="c7">
      <property name="widget">text</property>
      <property name="title">Nom</property>
      <property name="position">top</property>
      <property name="section">default</property>
      <property name="hidden">0</property>
      <property name="index">SearchableText</property>
      <property name="default" />
      <property name="onlyallelements">1</property>
      <property name="wildcard">1</property>
    </criterion>
    <criterion name="c8">
      <property name="widget">checkbox</property>
      <property name="title">Faceta 1</property>
      <property name="position">center</property>
      <property name="section">default</property>
      <property name="hidden">0</property>
      <property name="count">0</property>
      <property name="sortcountable">0</property>
      <property name="hidezerocount">1</property>
      <property name="index">en_faceta_1</property>
      <property name="operator">or</property>
      <property name="operator_visible">0</property>
      <property name="vocabulary">genweb.serveistic.vocabularies.enfaceta1</property>
      <property name="catalog" />
      <property name="maxitems">20</property>
      <property name="sortreversed">0</property>
      <property name="default" />
    </criterion>
    <criterion name="c3">
      <property name="widget">checkbox</property>
      <property name="title">Faceta 2</property>
      <property name="position">center</property>
      <property name="section">default</property>
      <property name="hidden">0</property>
      <property name="count">0</property>
      <property name="sortcountable">0</property>
      <property name="hidezerocount">1</property>
      <property name="index">en_faceta_2</property>
      <property name="operator">or</property>
      <property name="operator_visible">0</property>
      <property name="vocabulary">genweb.serveistic.vocabularies.enfaceta2</property>
      <property name="catalog" />
      <property name="maxitems">20</property>
      <property name="sortreversed">0</property>
      <property name="default" />
    </criterion>
    <criterion name="c6">
      <property name="widget">checkbox</property>
      <property name="title">Faceta 3</property>
      <property name="position">center</property>
      <property name="section">default</property>
      <property name="hidden">0</property>
      <property name="count">0</property>
      <property name="sortcountable">0</property>
      <property name="hidezerocount">1</property>
      <property name="index">en_faceta_3</property>
      <property name="operator">or</property>
      <property name="operator_visible">0</property>
      <property name="vocabulary">genweb.serveistic.vocabularies.enfaceta3</property>
      <property name="catalog" />
      <property name="maxitems">20</property>
      <property name="sortreversed">0</property>
      <property name="default" />
    </criterion>
    <criterion name="c5">
      <property name="widget">checkbox</property>
      <property name="title">Faceta 4</property>
      <property name="position">center</property>
      <property name="section">default</property>
      <property name="hidden">0</property>
      <property name="count">0</property>
      <property name="sortcountable">0</property>
      <property name="hidezerocount">1</property>
      <property name="index">en_faceta_4</property>
      <property name="operator">or</property>
      <property name="operator_visible">0</property>
      <property name="vocabulary">genweb.serveistic.vocabularies.enfaceta4</property>
      <property name="catalog" />
      <property name="maxitems">20</property>
      <property name="sortreversed">0</property>
      <property name="default" />
    </criterion>
    <criterion name="c4">
      <property name="widget">checkbox</property>
      <property name="title">Faceta 5</property>
      <property name="position">center</property>
      <property name="section">default</property>
      <property name="hidden">0</property>
      <property name="count">0</property>
      <property name="sortcountable">0</property>
      <property name="hidezerocount">1</property>
      <property name="index">en_faceta_5</property>
      <property name="operator">or</property>
      <property name="operator_visible">0</property>
      <property name="vocabulary">genweb.serveistic.vocabularies.enfaceta5</property>
      <property name="catalog" />
      <property name="maxitems">20</property>
      <property name="sortreversed">0</property>
      <property name="default" />
    </criterion>
    <criterion name="c9">
      <property name="widget">checkbox</property>
      <property name="title">Faceta 6</property>
      <property name="position">center</property>
      <property name="section">default</property>
      <property name="hidden">0</property>
      <property name="count">0</property>
      <property name="sortcountable">0</property>
      <property name="hidezerocount">1</property>
      <property name="index">en_faceta_6</property>
      <property name="operator">or</property>
      <property name="operator_visible">0</property>
      <property name="vocabulary">genweb.serveistic.vocabularies.enfaceta6</property>
      <property name="catalog" />
      <property name="maxitems">20</property>
      <property name="sortreversed">0</property>
      <property name="default" />
    </criterion>
    <criterion name="c10">
      <property name="widget">checkbox</property>
      <property name="title">Faceta 7</property>
      <property name="position">center</property>
      <property name="section">default</property>
      <property name="hidden">0</property>
      <property name="count">0</property>
      <property name="sortcountable">0</property>
      <property name="hidezerocount">0</property>
      <property name="index">en_faceta_7</property>
      <property name="operator">or</property>
      <property name="operator_visible">0</property>
      <property name="vocabulary">genweb.serveistic.vocabularies.enfaceta7</property>
      <property name="catalog" />
      <property name="maxitems">20</property>
      <property name="sortreversed">0</property>
      <property name="default" />
    </criterion>
    <criterion name="c11">
      <property name="widget">checkbox</property>
      <property name="title">Faceta 8</property>
      <property name="position">center</property>
      <property name="section">default</property>
      <property name="hidden">0</property>
      <property name="count">0</property>
      <property name="sortcountable">0</property>
      <property name="hidezerocount">1</property>
      <property name="index">en_faceta_8</property>
      <property name="operator">or</property>
      <property name="operator_visible">0</property>
      <property name="vocabulary">genweb.serveistic.vocabularies.enfaceta8</property>
      <property name="catalog" />
      <property name="maxitems">20</property>
      <property name="sortreversed">0</property>
      <property name="default" />
    </criterion>
    <criterion name="c0">
      <property name="widget">resultsperpage</property>
      <property name="title">Results per page</property>
      <property name="position">right</property>
      <property name="section">default</property>
      <property name="hidden">1</property>
      <property name="start" />
      <property name="end">1000</property>
      <property name="step">50</property>
      <property name="default">100</property>
    </criterion>
    <criterion name="c1">
      <property name="widget">checkbox</property>
      <property name="title">Portal type</property>
      <property name="position">right</property>
      <property name="section">default</property>
      <property name="hidden">1</property>
      <property name="count">1</property>
      <property name="hidezerocount" />
      <property name="index">portal_type</property>
      <property name="operator">and</property>
      <property name="vocabulary">eea.facetednavigation.vocabularies.FacetedPortalTypes</property>
      <property name="catalog" />
      <property name="maxitems">5</property>
      <property name="sortreversed">1</property>
      <property name="default">serveitic</property>
    </criterion>
    <criterion name="c2">
      <property name="widget">sorting</property>
      <property name="title">Sort on</property>
      <property name="position">right</property>
      <property name="section">default</property>
      <property name="hidden">1</property>
      <property name="vocabulary" />
      <property name="default">sortable_title</property>
    </criterion>
    <criterion name="c12">
      <property name="widget">resultsfilter</property>
      <property name="title">Path</property>
      <property name="position">right</property>
      <property name="section">default</property>
      <property name="hidden">1</property>
      <property name="default">python:'/en/' in brain.getObject().absolute_url_path()</property>
    </criterion>
  </criteria>
</object>
